api/__init__.py
api/__version__.py
api/config.py
api/dependencies.py
api/exceptions.py
api/main.py
api/helpers/__init__.py
api/helpers/blob.py
api/middleware/__init__.py
api/middleware/error_handling_middleware.py
api/routers/__init__.py
api/routers/data.py
api/routers/home.py
api/routers/vercel_blob.py
api/services/__init__.py
api/services/blob_storage.py
njmtech_upload_blob-0.1.1.dist-info/licenses/LICENSE.md
njmtech_upload_blob-0.1.1.dist-info/METADATA
njmtech_upload_blob-0.1.1.dist-info/WHEEL
njmtech_upload_blob-0.1.1.dist-info/top_level.txt
njmtech_upload_blob-0.1.1.dist-info/RECORD
