Metadata-Version: 2.4
Name: njmtech-upload-blob
Version: 0.1.1
Summary: This is a simple FastAPI application to upload files to Vercel Blob storage.
Requires-Python: >=3.11
License-File: LICENSE.md
Requires-Dist: fastapi[standard]
Requires-Dist: uvicorn
Requires-Dist: python-dotenv
Requires-Dist: vercel-blob
Requires-Dist: python-multipart
Requires-Dist: pydantic
Requires-Dist: Werkzeug
Dynamic: license-file
